wootils/__init__.py
wootils/filters.py
wootils/fitters.py
wootils/inpex23_filtfunc.py
wootils/linalg.py
wootils/ofreqs.py
wootils/plotnice.py
wootils/plottimeseries.py
wootils/sigint.py
wootils/tidepred_funcs.py
wootils/time_wutils.py
wootils-0.0.3.dist-info/LICENSE
wootils-0.0.3.dist-info/METADATA
wootils-0.0.3.dist-info/WHEEL
wootils-0.0.3.dist-info/entry_points.txt
wootils-0.0.3.dist-info/top_level.txt
wootils-0.0.3.dist-info/RECORD
