Metadata-Version: 2.1
Name: wootils
Version: 0.0.3
Summary: Python package for commonly used code.
Home-page: https://github.com/williamedge/wootils
Author: William Edge
Author-email: william.edge@uwa.edu.au
License: BSD-3-Clause
Project-URL: Bug Tracker, https://github.com/williamedge/wootils/issues
Project-URL: Changelog, https://github.com/williamedge/wootils/releases
Classifier: Programming Language :: Python :: 3
Classifier: License :: OSI Approved :: BSD License
Classifier: Intended Audience :: Developers
Requires-Python: >=3.7
License-File: LICENSE
Requires-Dist: numpy
Requires-Dist: scipy
Requires-Dist: xarray
Requires-Dist: matplotlib
Requires-Dist: pandas
